petit_downloader/__init__.py
petit_downloader/constants.py
petit_downloader/data_struct.py
petit_downloader/download.py
petit_downloader/download_container.py
petit_downloader/download_methods.py
petit_downloader/utils.py
petit_downloader-0.1.7.dist-info/LICENSE.txt
petit_downloader-0.1.7.dist-info/METADATA
petit_downloader-0.1.7.dist-info/WHEEL
petit_downloader-0.1.7.dist-info/top_level.txt
petit_downloader-0.1.7.dist-info/RECORD
