Metadata-Version: 2.1
Name: petit-downloader
Version: 0.1.7
Summary: Download files in an easier way
Home-page: https://github.com/Plawn/petit_downloader
Author: Plawn
Author-email: plawn.yay@gmail.com
License: apache-2.0
Platform: UNKNOWN
